{"cameraMode":{"drawMode":0,"name":"Shaded","section":"Shading Mode"},"sceneLighting":true,"audioPlay":false,"sceneViewState":{"m_AlwaysRefresh":false,"showFog":true,"showSkybox":true,"showFlares":true,"showImageEffects":true,"showParticleSystems":true,"showVisualEffectGraphs":true,"m_FxEnabled":true},"in2DMode":false,"pivot":{"x":386.33203125,"y":1.2039999961853028,"z":-452.9220275878906},"rotation":{"x":-0.014568504877388478,"y":0.9729598164558411,"z":0.06400566548109055,"w":0.22145886719226838},"size":1.2247447967529297,"orthographic":false}